Code/CGESystem.py
Code/Calibration.py
Code/Consumer.py
Code/MacroEconomy.py
Code/Producer.py
Code/Run.py
Code/__init__.py
CGETeaching_Project-0.1.dist-info/METADATA
CGETeaching_Project-0.1.dist-info/WHEEL
CGETeaching_Project-0.1.dist-info/entry_points.txt
CGETeaching_Project-0.1.dist-info/top_level.txt
CGETeaching_Project-0.1.dist-info/RECORD
